setup.cfg
setup.py
filmapis/_init_.py
filmapis/filmapis.py
filmapis.egg-info/PKG-INFO
filmapis.egg-info/SOURCES.txt
filmapis.egg-info/dependency_links.txt
filmapis.egg-info/not-zip-safe
filmapis.egg-info/top_level.txt