Metadata-Version: 2.1
Name: filmapis
Version: 0.0
Summary: Gaussian and Binomial distributions
Home-page: UNKNOWN
Author-email: swintages@gmail.com
License: UNKNOWN
Platform: UNKNOWN
